pyserilog/__init__.py
pyserilog/guard.py
pyserilog/ilogger.py
pyserilog/logger_configuration.py
pyserilog/utils.py
pyserilog/capturing/__init__.py
pyserilog/capturing/depth_limiter.py
pyserilog/capturing/iproperty_value_converter.py
pyserilog/capturing/message_template_processor.py
pyserilog/capturing/property_binder.py
pyserilog/capturing/property_value_converter.py
pyserilog/configuration/__init__.py
pyserilog/configuration/ilogger_settings.py
pyserilog/configuration/logger_audit_sink_configuration.py
pyserilog/configuration/logger_destructuring_configuration.py
pyserilog/configuration/logger_enrichment_configuration.py
pyserilog/configuration/logger_filter_configuration.py
pyserilog/configuration/logger_minimum_level_configuration.py
pyserilog/configuration/logger_settings_configuration.py
pyserilog/configuration/logger_sink_configuration.py
pyserilog/context/__init__.py
pyserilog/context/log_context.py
pyserilog/context/log_context_enricher.py
pyserilog/core/__init__.py
pyserilog/core/constants.py
pyserilog/core/idestructuring_policy.py
pyserilog/core/ilog_event_enricher.py
pyserilog/core/ilog_event_filter.py
pyserilog/core/ilog_event_property_factory.py
pyserilog/core/ilog_event_property_value_factory.py
pyserilog/core/ilog_event_sink.py
pyserilog/core/imessage_template_parser.py
pyserilog/core/iscalar_conversion_policy.py
pyserilog/core/level_override_map.py
pyserilog/core/logger.py
pyserilog/core/logging_level_switch.py
pyserilog/core/string_writable.py
pyserilog/core/enrichers/__init__.py
pyserilog/core/enrichers/conditional_enricher.py
pyserilog/core/enrichers/empty_enricher.py
pyserilog/core/enrichers/fixed_property_enricher.py
pyserilog/core/enrichers/property_enricher.py
pyserilog/core/enrichers/safe_aggregate_enricher.py
pyserilog/core/filter/__init__.py
pyserilog/core/filter/delegate_filter.py
pyserilog/core/pipeline/__init__.py
pyserilog/core/pipeline/message_template_cache.py
pyserilog/core/pipeline/silet_logger.py
pyserilog/core/sinks/__init__.py
pyserilog-0.3.3.dist-info/METADATA
pyserilog-0.3.3.dist-info/WHEEL
pyserilog-0.3.3.dist-info/top_level.txt
pyserilog-0.3.3.dist-info/RECORD
